Workbook

Sheet ME MS
A2: MS IN MECHANICAL ENGINEERING
A3: This is for planning purposes only. This plan is only approved once you receive confirmation from your advisor.
A4: Students can choose one of two options to fulfill their Master's degree requirements: the "All-Course" option or the "Thesis" option. The requirements for both options are summarized below. ALL COURSE OPTION: Students completing the “all-course” option must take a coordinated sequence of ten courses. All courses must be completed within five years from the start of the student’s first class. Students are required to choose a focus area to follow. The focus area selected does not appear as an official designation on the student transcript. The curriculum consists of one core course in mathematics, two core courses from Group 1 and three other courses from Group 2 of the student’s chosen focus area, and four technical electives. At least two of the four electives must be from a core engineering discipline, and at most two can be chosen from the Engineering Management, Systems Engineering, Space Systems Engineering, Information Systems Engineering, Healthcare Systems Engineering, Cybersecurity, Financial Mathematics, Occupational and Environmental Hygiene, or Environmental Planning and Management programs. THESIS OPTION: Students completing the “thesis” option must take a coordinated sequence of eight courses and prepare and submit a Master’s thesis. All requirements should be completed within five years. Students are required to choose a focus area to follow. The focus area selected does not appear as an official designation on the student transcript. The curriculum consists of one core course in mathematics, two core courses from those listed in Group 1 and three courses from those listed in Group 2 of the student’s chosen focus area, two technical electives, and a thesis. Please see catalog for more information.
A6: Link to when courses are being offered: | B6: https://ep.jhu.edu/wp-content/uploads/2020/09/scheduleplan-me.pdf
A7: Link to website: | B7: https://ep.jhu.edu/programs/mechanical-engineering/
A8: Link to catalog: | B8: https://e-catalogue.jhu.edu/engineering/engineering-professionals/mechanical-engineering/mechanical-engineering-master-science/
A9: *** ATTENTION: Aerosapce Engineering - General is only for students addmitted before Spring 2026
B10: FOCUS AREAS/CONC | C10: *** STEP 1: SELECT FROM LIST ***
C12: Course Name | D12: Semester Planned/Taken* | E12: Successfully completed (y/n)?) | F12: Course description
A13: Core | B13: Core Courses
A14: Math Core Course | B14: EN.535.641 | C14: Mathematical Methods For Engineers (ANY SECTION IS OK) | D14: SP 26 | E14: NO
A15: Focus Area | B15: Focus Area Courses
A16: Group 1 Focus Area Course | B16: *** STEP 02: SELECT GROUP 1 *** | C16: =_xlfn.XLOOKUP(B16,cs!C:C,cs!D:D,"Not Found") -> Not Found | D16: SP 26 | E16: NO | F16: =_xlfn.XLOOKUP(B16,cs!C:C,cs!R:R,"Not Found") -> Not Found
A17: Group 1 Focus Area Course | B17: *** STEP 03: SELECT GROUP 1 *** | C17: =_xlfn.XLOOKUP(B17,cs!C:C,cs!D:D,"Not Found") -> Not Found | D17: SP 21 | E17: NO | F17: =_xlfn.XLOOKUP(B17,cs!C:C,cs!R:R,"Not Found") -> Not Found
A18: Group 2 Focus Area Course | B18: *** STEP 04: SELECT GROUP 1 OR 2 *** | C18: =_xlfn.XLOOKUP(B18,cs!C:C,cs!D:D,"Not Found") -> Not Found | D18: FA 21 | E18: NO | F18: {=_xlfn.XLOOKUP(B18,cs!C:C,cs!$R:R,"Not Found")} -> Not Found
A19: Group 2 Focus Area Course | B19: *** STEP 05: SELECT GROUP 1 OR 2 *** | C19: =_xlfn.XLOOKUP(B19,cs!C:C,cs!D:D,"Not Found") -> Not Found | D19: SU 21 | E19: NO | F19: {=_xlfn.XLOOKUP(B19,cs!C:C,cs!$R:R,"Not Found")} -> Not Found
A20: Group 2 Focus Area Course | B20: *** STEP 06: SELECT GROUP 1 OR 2 *** | C20: =_xlfn.XLOOKUP(B20,cs!C:C,cs!D:D,"Not Found") -> Not Found | D20: SU 23 | E20: NO | F20: {=_xlfn.XLOOKUP(B20,cs!C:C,cs!$R:R,"Not Found")} -> Not Found
A21: Technical Electives | B21: Additional classes
A22: Technical Elective | B22: *** STEP 07: SELECT ELECTIVES *** | C22: =_xlfn.XLOOKUP(B22,cs!C:C,cs!D:D,"Not Found") -> Not Found | D22: FA 21 | E22: NO | F22: {=_xlfn.XLOOKUP(B22,cs!C:C,cs!$R:R,"Not Found")} -> Not Found
A23: Technical Elective | B23: *** STEP 08: SELECT ELECTIVES *** | C23: =_xlfn.XLOOKUP(B23,cs!C:C,cs!D:D,"Not Found") -> Not Found | D23: SU 21 | E23: NO | F23: {=_xlfn.XLOOKUP(B23,cs!C:C,cs!$R:R,"Not Found")} -> Not Found
A24: Technical Elective/Thesis | B24: *** STEP 09: SELECT ELECTIVES *** | C24: =_xlfn.XLOOKUP(B24,cs!C:C,cs!D:D,"Not Found") -> Not Found | D24: FA 21 | E24: NO | F24: {=_xlfn.XLOOKUP(B24,cs!C:C,cs!$R:R,"Not Found")} -> Not Found
A25: Technical Elective/Thesis | B25: *** STEP 10: SELECT ELECTIVES *** | C25: =_xlfn.XLOOKUP(B25,cs!C:C,cs!D:D,"Not Found") -> Not Found | D25: FA 21 | E25: NO | F25: {=_xlfn.XLOOKUP(B25,cs!C:C,cs!$R:R,"Not Found")} -> Not Found
A26: *Course Enrollment is subject to offering and space availability and is not guaranteed by advisor approval of the academic plan.
A27: ***ATTENTION: Ensure Not Selecting Duplicates | F27: ***ATTENTION: Ensure No more than 1 recommended/computational course for Group 2 | you can take as many computational course as you want as core engineering electives
A28: {=IF(MAX(COUNTIF(B14:B25, B14:B25))>1, "*** ATTENTION: FOUND DUPLICATED COURSES!", "No Duplicates")} -> No Duplicates
A29: If your admissions letter required you to take pre-requisite coursework, list those requirements here:
A30: Pre-requisites required | B30: Course Number | C30: Course Name | D30: Semester Planned/Taken* | E30: Successfully completed (y/n)?)
A31: Pre-requisite course | D31: FA 21 | E31: YES
A32: Pre-requisite course | D32: SP 23 | E32: YES
A33: Pre-requisite course | D33: FA 23 | E33: YES
A34: Pre-requisite course | D34: SP 23 | E34: YES
A35: Pre-requisite course | D35: SP 23 | E35: YES
A36: Pre-requisite course | D36: SP 22 | E36: YES
A39: NOTES:

Sheet cs
B1: Program | C1: Course Number | D1: Course Title | E1: Course Credits | F1: Advanced Manufacturing | G1: Aerospace Engineering - Aerodynamics | H1: Aerospace Engineering - Dynamics and Control | I1: Aerospace Engineering - Structures and Materials | J1: Aerospace Engineering - Vehicle Design | K1: Biomechanical Engineering | L1: Fluid and Thermal Mechanics | M1: Hypersonic Technologies | N1: Mechanics of Materials and Structures | O1: Ocean Engineering | P1: Robotics, Dynamics, and Controls | Q1: Course Description
A2: 0 | B2: ep_mechanical_engineering | C2: EN.535.603 | D2: Applied Optimal Control | E2: 3 | F2: Elective (Core Engineering Discipline) | G2: Elective (Core Engineering Discipline) | H2: Elective (Core Engineering Discipline) | I2: Elective (Core Engineering Discipline) | J2: Elective (Core Engineering Discipline) | K2: Elective (Core Engineering Discipline) | L2: Elective (Core Engineering Discipline) | M2: Elective (Core Engineering Discipline) | N2: Elective (Core Engineering Discipline) | O2: Elective (Core Engineering Discipline) | P2: Group 2 & Elective (Core Engineering Discipline) | Q2: The course focuses on the optimal control of dynamical systems subject to constraints and uncertainty by studying analytical and computational methods leading to practical algorithms. Topics include calculus of variations, nonlinear local optimization, global stochastic search, dynamic programming, linear quadratic (gaussian) control, numerical trajectory optimization, model-predictive control. Advanced topics include approximate dynamic programming and optimal control on manifolds. The methods and algorithms will be illustrated through implementation of various simulated examples. Recommended Course Background: Linear Algebra and Differential Equations; experience with control systems; programming in MATLAB and/or Python.
A3: 1 | B3: ep_mechanical_engineering | C3: EN.535.606 | D3: Advanced Strength Of Materials | E3: 3 | F3: Elective (Core Engineering Discipline) | G3: Elective (Core Engineering Discipline) | H3: Elective (Core Engineering Discipline) | I3: Group 1, Group 2, & Electives (Core Engineering Discipline) | J3: Group 2 & Elective (Core Engineering Discipline) | K3: Elective (Core Engineering Discipline) | L3: Elective (Core Engineering Discipline) | M3: Elective (Core Engineering Discipline) | N3: Group 1, Group 2, & Electives (Core Engineering Discipline) | O3: Group 1, Group 2, & Electives (Core Engineering Discipline) | P3: Elective (Core Engineering Discipline) | Q3: This course reviews stress and strain in three dimensions, elastic and inelastic material behavior, and energy methods. It also covers use of the strength of materials approach to solving advanced problems of torsion and bending of beams. Prerequisite(s): Fundamental understanding of stress and strain and axial, torsion, and bending effects in linear elastic solids.
A4: 2 | B4: ep_mechanical_engineering | C4: EN.535.607 | D4: Mechanics of Solids and Structures: Theory and Applications I | E4: 3 | F4: Elective (Core Engineering Discipline) | G4: Elective (Core Engineering Discipline) | H4: Elective (Core Engineering Discipline) | I4: Group 1, Group 2, & Electives (Core Engineering Discipline) | J4: Group 2 & Elective (Core Engineering Discipline) | K4: Elective (Core Engineering Discipline) | L4: Elective (Core Engineering Discipline) | M4: Elective (Core Engineering Discipline) | N4: Group 1, Group 2, & Electives (Core Engineering Discipline) | O4: Group 2 & Elective (Core Engineering Discipline) | P4: Elective (Core Engineering Discipline) | Q4: This course provides an introduction to the mathematical and theoretical foundations of the mechanics of solids and structures. We will begin with the mathematical preliminaries used in continuum mechanics: vector and tensor calculus, then introduce 3D kinematics and strain measures, descriptions of stress in a 3D body, equilibrium, and constitutive rules. These concepts will be applied to develop the constitutive equations for solids, methods for solving boundary values problems that occur in engineering structures, energy methods and foundations of large deformation.
A5: 3 | B5: ep_mechanical_engineering | C5: EN.535.608 | D5: Hypersonic Technologies and Systems | E5: 3 | F5: Elective (Core Engineering Discipline) | G5: Group 1, Group 2, & Electives (Core Engineering Discipline) | H5: Group 1, Group 2, & Electives (Core Engineering Discipline) | I5: Group 2 & Elective (Core Engineering Discipline) | J5: Group 1, Group 2, & Electives (Core Engineering Discipline) | K5: Elective (Core Engineering Discipline) | L5: Elective (Core Engineering Discipline) | M5: Group 1, Group 2, & Electives (Core Engineering Discipline) | N5: Elective (Core Engineering Discipline) | O5: Elective (Core Engineering Discipline) | P5: Elective (Core Engineering Discipline) | Q5: “Hypersonics” is a general term used to describe flight at speeds greater than Mach 5 (or five times the sound speed). The technologies associated with hypersonic flight have been investigated for many decades and applications of hypersonic systems currently include ballistic missiles, re-entry vehicles, launch vehicles, and interceptor missiles. There is currently a resurgence in interest in new hypersonic applications for weapon applications, reusable aircraft, and reusable space launchers. With a view towards the history of hypersonics and developing worldwide trends, this course provides a survey of hypersonic technologies, systems and applications while addressing the underlying fundamental physics, analysis approaches, and design methodologies.
A6: 4 | B6: ep_mechanical_engineering | C6: EN.535.610 | D6: Computational Methods of Analysis | E6: 3 | F6: Group 2 (Computational/Recommended) & Elective (Core Engineering Discipline) | G6: Group 2 (Computational/Recommended) & Elective (Core Engineering Discipline) | H6: Group 2 (Computational/Recommended) & Elective (Core Engineering Discipline) | I6: Group 2 (Computational/Recommended) & Elective (Core Engineering Discipline) | J6: Group 2 (Computational/Recommended) & Elective (Core Engineering Discipline) | K6: Group 2 (Computational/Recommended) & Elective (Core Engineering Discipline) | L6: Group 2 (Computational/Recommended) & Elective (Core Engineering Discipline) | M6: Group 2 (Computational/Recommended) & Elective (Core Engineering Discipline) | N6: Group 2 (Computational/Recommended) & Elective (Core Engineering Discipline) | O6: Group 2 (Computational/Recommended) & Elective (Core Engineering Discipline) | P6: Group 2 (Computational/Recommended) & Elective (Core Engineering Discipline) | Q6: This course will provide an introduction to computational methods of analysis, with the aim of preparing the student to take a real-world problem and break it down to its component parts, perform computational analysis, and report findings in a comprehensive and informative manner. This course introduces the student to several application areas, and the corresponding computational tools, assumptions, and limitations. Throughout the course, the student will solve problems computationally in a hands-on manner, with a particular emphasis on tradeoffs between complexity, cost, and utility.
A7: 5 | B7: ep_mechanical_engineering | C7: EN.535.612 | D7: Intermediate Dynamics | E7: 3 | F7: Elective (Core Engineering Discipline) | G7: Elective (Core Engineering Discipline) | H7: Group 2 & Elective (Core Engineering Discipline) | I7: Group 2 & Elective (Core Engineering Discipline) | J7: Elective (Core Engineering Discipline) | K7: Elective (Core Engineering Discipline) | L7: Elective (Core Engineering Discipline) | M7: Elective (Core Engineering Discipline) | N7: Group 2 & Elective (Core Engineering Discipline) | O7: Elective (Core Engineering Discipline) | P7: Group 2 & Elective (Core Engineering Discipline) | Q7: This course develops student’s ability to accurately model the dynamics of single and multi-body engineering systems undergoing motion in 3D space. The course begins with formulating the differential geometry and kinematics of curvilinear coordinates to permit kinematic descriptions of relative motion and rotation of rigid bodies and mechanisms subject to common engineering constraints such as substructure interconnections, dry friction, and rolling. Momentum and inertia properties of rigid body dynamics follow. Students are then introduced to analytical dynamics, where Lagrange’s equations and Kane’s method are derived and studied to facilitate efficient formulation of the equations of motion governing the dynamics of systems subject to conservative and non-conservative forces and engineering constraints. The course also concludes with gyroscopic dynamics with applications to inertial guidance and spacecraft attitude dynamics. Prerequisite(s): Mathematics through calculus and linear algebra.
A8: 6 | B8: ep_mechanical_engineering | C8: EN.535.613 | D8: Structural Dynamics and Stability | E8: 3 | F8: Elective (Core Engineering Discipline) | G8: Elective (Core Engineering Discipline) | H8: Elective (Core Engineering Discipline) | I8: Elective (Core Engineering Discipline) | J8: Elective (Core Engineering Discipline) | K8: Elective (Core Engineering Discipline) | L8: Elective (Core Engineering Discipline) | M8: Elective (Core Engineering Discipline) | N8: Elective (Core Engineering Discipline) | O8: Elective (Core Engineering Discipline) | P8: Elective (Core Engineering Discipline) | Q8: This course introduces the propagation of elastic waves, and the loss of stability in engineering structures and systems. In the first part of the course, fundamental physical principles of elasticity and wave mechanics are reviewed and developed to provide students with the capability to model and analyze wave propagation, reflection, and refraction in isotropic and anisotropic engineering structures such as rods, beams, and plates. In the second part of the course, mechanical stability models are studied and applied in terms of dynamic behavior where the combined effects of vibration, gyroscopic motion, impact/shock, and buckling lead to new structural configurations or unstable motions that must often be avoided in design. Applications span nondestructive evaluation, composites, cables, aircraft/space structures, rotordynamics, aeroelasticity, civil engineering structures, and others. Prerequisite(s): Undergraduate or graduate course in vibrations.
A9: 7 | B9: ep_mechanical_engineering | C9: EN.535.614 | D9: Fundamentals of Acoustics | E9: 3 | F9: Elective (Core Engineering Discipline) | G9: Elective (Core Engineering Discipline) | H9: Elective (Core Engineering Discipline) | I9: Elective (Core Engineering Discipline) | J9: Elective (Core Engineering Discipline) | K9: Elective (Core Engineering Discipline) | L9: Group 2 & Elective (Core Engineering Discipline) | M9: Elective (Core Engineering Discipline) | N9: Elective (Core Engineering Discipline) | O9: Group 2 & Elective (Core Engineering Discipline) | P9: Elective (Core Engineering Discipline) | Q9: This course introduces the physical principles of acoustics and their application. Fundamental topics include the generation, transmission, and reception of acoustic waves. Applications covered are selected from acoustic arrays, underwater acoustics, architectural acoustics, and biomedical acoustics. Prerequisite(s): Some familiarity with linear algebra, complex variables, and differential equations.
A10: 8 | B10: ep_mechanical_engineering | C10: EN.535.618 | D10: Fabricatology - Advanced Materials Processing | E10: 3 | F10: Group 2 & Elective (Core Engineering Discipline) | G10: Elective (Core Engineering Discipline) | H10: Elective (Core Engineering Discipline) | I10: Elective (Core Engineering Discipline) | J10: Elective (Core Engineering Discipline) | K10: Elective (Core Engineering Discipline) | L10: Elective (Core Engineering Discipline) | M10: Elective (Core Engineering Discipline) | N10: Group 2 & Elective (Core Engineering Discipline) | O10: Elective (Core Engineering Discipline) | P10: Elective (Core Engineering Discipline) | Q10: The “Fabricatology” is a course that students can learn how to make desired shapes, structures, and surfaces across various length scales. It will introduce rich scientific and engineering knowledge related to fabrication at multiple length scales and the generated materials and mechanical systems can be utilized for studying diverse topics including energy harvesting, metamaterials, wetting, and information storage. From this course, students can learn principles and technologies to control shapes at various length scales and processes to control internal structures or surface properties for desired properties/functions. They will be also introduced to exciting recent developments in the field such as 3D printing so that they can have a comprehensive knowledge about the subject.
A11: 9 | B11: ep_mechanical_engineering | C11: EN.535.620 | D11: Fluid Dynamics I | E11: 3 | F11: Elective (Core Engineering Discipline) | G11: Group 1, Group 2, & Electives (Core Engineering Discipline) | H11: Elective (Core Engineering Discipline) | I11: Elective (Core Engineering Discipline) | J11: Elective (Core Engineering Discipline) | K11: Elective (Core Engineering Discipline) | L11: Group 1, Group 2, & Electives (Core Engineering Discipline) | M11: Elective (Core Engineering Discipline) | N11: Elective (Core Engineering Discipline) | O11: Group 1, Group 2, & Electives (Core Engineering Discipline) | P11: Elective (Core Engineering Discipline) | Q11: This first graduate course in fluid dynamics starts from derivation of the flow equations and examines a number of limiting behaviors. When viscous effects are ignored all together, we obtain the familiar limit of potential flow. Boundary layer theory is introduced to examine the effect of viscosity near surfaces. And in the limit where viscosity is dominant, we obtain what is known as “creeping flow” where inertia can be ignored all together. Our approach will rely on developing the theory and considering classical examples in order to advance our understanding of fluid motion in each of these areas.
A12: 10 | B12: ep_mechanical_engineering | C12: EN.535.621 | D12: Intermediate Fluid Dynamics | E12: 3 | F12: Elective (Core Engineering Discipline) | G12: Elective (Core Engineering Discipline) | H12: Elective (Core Engineering Discipline) | I12: Elective (Core Engineering Discipline) | J12: Elective (Core Engineering Discipline) | K12: Elective (Core Engineering Discipline) | L12: Elective (Core Engineering Discipline) | M12: Elective (Core Engineering Discipline) | N12: Elective (Core Engineering Discipline) | O12: Elective (Core Engineering Discipline) | P12: Elective (Core Engineering Discipline) | Q12: This course prepares the student to solve practical engineering flow problems and concentrates on the kinematics and dynamics of viscous fluid flows. Topics include the control volume and differential formulations of the conservation laws, including the Navier-Stokes equations. Students examine vorticity and circulation, dynamic similarity, and laminar and turbulent flows. The student is exposed to analytical techniques and experimental methods, and the course includes an introduction to computational methods in fluid dynamics. It also includes a programming project to develop a numerical solution to a practical fluid flow problem. Prerequisite(s): An undergraduate fluid mechanics course.
A13: 11 | B13: ep_mechanical_engineering | C13: EN.535.622 | D13: Robot Motion Planning | E13: 3 | F13: Elective (Core Engineering Discipline) | G13: Elective (Core Engineering Discipline) | H13: Elective (Core Engineering Discipline) | I13: Elective (Core Engineering Discipline) | J13: Elective (Core Engineering Discipline) | K13: Elective (Core Engineering Discipline) | L13: Elective (Core Engineering Discipline) | M13: Elective (Core Engineering Discipline) | N13: Elective (Core Engineering Discipline) | O13: Elective (Core Engineering Discipline) | P13: Group 2 & Elective (Core Engineering Discipline) | Q13: This course investigates the motion planning problem in robotics. Topics include motion of rigid objects by the configurations space and retraction approaches, shortest path motion, motion of linked robot arms, compliant motion, coordinated motion of several objects, robust motion with error detection and recovery, and motion in an unknown environment
... A884: 882 | B884: systems_engineering | C884: EN.645.711 | D884: Systems Engineering of Radar and Missile Technologies | E884: 3 | F884: Elective (Non-Core Engineering Discipline) | G884: Elective (Non-Core Engineering Discipline) | H884: Elective (Non-Core Engineering Discipline) | I884: Elective (Non-Core Engineering Discipline) | J884: Elective (Non-Core Engineering Discipline) | K884: Elective (Non-Core Engineering Discipline) | L884: Elective (Non-Core Engineering Discipline) | M884: Elective (Non-Core Engineering Discipline) | N884: Elective (Non-Core Engineering Discipline) | O884: Elective (Non-Core Engineering Discipline) | P884: Elective (Non-Core Engineering Discipline) | Q884: This course emphasizes the key systems engineering processes involved in missile design. Missile technologies including electro-optical and radio-frequency sensors used for target detection; aerodynamics; navigation, guidance, and control; propulsion; warheads; fuzes; and signal and image processing are discussed in conjunction with the critical tradeoffs and methods used to meet operational requirements. The course objectives are demonstrated through a system cost-as-an-independent variable trade and design study that is based on trades of sensor type, guidance type, operational constraints and implementation, and how the system is segregated into different sub-system configurations.
B885: systems_engineering | C885: EN.645.742 | D885: Management of Complex Systems | E885: 3 | F885: Elective (Non-Core Engineering Discipline) | G885: Elective (Non-Core Engineering Discipline) | H885: Elective (Non-Core Engineering Discipline) | I885: Elective (Non-Core Engineering Discipline) | J885: Elective (Non-Core Engineering Discipline) | K885: Elective (Non-Core Engineering Discipline) | L885: Elective (Non-Core Engineering Discipline) | M885: Elective (Non-Core Engineering Discipline) | N885: Elective (Non-Core Engineering Discipline) | O885: Elective (Non-Core Engineering Discipline) | P885: Elective (Non-Core Engineering Discipline) | Q885: Traditional systems engineering is usually applied to closed, precise, and recursive systems with the assertion that the methodologies used can be scaled up to more elaborate systems of systems. This course addresses the more realistic and emerging field of complex systems, where multiple current development efforts with disparate and nonlinear attributes characterize the system components. Managing complex systems must account for the likelihood of multiple disciplines, differing scales, often unpredictable future states, irreducible uncertainty, and nonlinear behavior. Customers, corporations, governments, technologies, and systems now must be considered on a global scale with a mix of new and legacy systems. The student will be encouraged to think differently and creatively about the approaches to managing complex systems and to use adaptive strategies and tools. Special attention will be given to risk assessment and management for dynamic systems. Case studies and examples will be drawn from commercial industry and DoD/government systems. Students will be expected to discuss several readings and complete academic papers to explore in depth one or more of the concepts discussed.
B886: systems_engineering | C886: EN.645.753 | D886: Enterprise Systems Engineering | E886: 3 | F886: Elective (Non-Core Engineering Discipline) | G886: Elective (Non-Core Engineering Discipline) | H886: Elective (Non-Core Engineering Discipline) | I886: Elective (Non-Core Engineering Discipline) | J886: Elective (Non-Core Engineering Discipline) | K886: Elective (Non-Core Engineering Discipline) | L886: Elective (Non-Core Engineering Discipline) | M886: Elective (Non-Core Engineering Discipline) | N886: Elective (Non-Core Engineering Discipline) | O886: Elective (Non-Core Engineering Discipline) | P886: Elective (Non-Core Engineering Discipline) | Q886: Enterprise Systems Engineering is a multidisciplinary approach to the application of systems engineering principles and systems thinking to large sociotechnical enterprises as complex adaptive systems. Health, energy, food, disaster response, and global transportation systems are all examples of such systems. Systems engineering has been a critical enabler of development, and is key, to addressing the complexities of the evolution of complex systems and systems of systems.?In this course, we explore systems thinking and systems engineering approaches that can be applied to this new class of broad sociotechnical enterprise.? We will examine the characteristics of this class of enterprise and the challenges for applying systems engineering to this type of complex adaptive system. These enterprises are comprised of multiple independent organizations with their own objectives, resources, and authority structures without top-level cross cutting authority and may possess conflicting objectives. A process model will be created to describe the activities of key enterprise elements and interactions which, along with external factors, influence the evolution of such enterprises. This model will be used to understand the current enterprise composition and dynamics and evaluate the impact of issues or actions as the basis for systems engineering trades or recommendations.
B887: systems_engineering | C887: EN.645.755 | D887: Methods in Human-System Performance Measurement and Analysis | E887: 3 | F887: Elective (Non-Core Engineering Discipline) | G887: Elective (Non-Core Engineering Discipline) | H887: Elective (Non-Core Engineering Discipline) | I887: Elective (Non-Core Engineering Discipline) | J887: Elective (Non-Core Engineering Discipline) | K887: Elective (Non-Core Engineering Discipline) | L887: Elective (Non-Core Engineering Discipline) | M887: Elective (Non-Core Engineering Discipline) | N887: Elective (Non-Core Engineering Discipline) | O887: Elective (Non-Core Engineering Discipline) | P887: Elective (Non-Core Engineering Discipline) | Q887: This course focuses on human-systems performance measurement (HsPM) methods used to determine whether human-system requirements are met and if the system’s design provides effective and efficient human-system performance. Students will gain knowledge of HsPM study design protocols, data collection tools and methods, analysis techniques and processes, and procedures required to execute studies with human participants. The course will provide students with an understanding of HsPM in the context of system design; workplace design; environment, safety, and occupational health; training; and maintenance. Students will be exposed to heuristic evaluations; modeling and simulation of human tasking, including tools for measuring physical limitations, cognitive load, and fatigue; and system testing with the human element.
B888: systems_engineering | C888: EN.645.756 | D888: Metrics, Modeling, and Simulation for Systems Engineering | E888: 3 | F888: Elective (Non-Core Engineering Discipline) | G888: Elective (Non-Core Engineering Discipline) | H888: Elective (Non-Core Engineering Discipline) | I888: Elective (Non-Core Engineering Discipline) | J888: Elective (Non-Core Engineering Discipline) | K888: Elective (Non-Core Engineering Discipline) | L888: Elective (Non-Core Engineering Discipline) | M888: Elective (Non-Core Engineering Discipline) | N888: Elective (Non-Core Engineering Discipline) | O888: Elective (Non-Core Engineering Discipline) | P888: Elective (Non-Core Engineering Discipline) | Q888: This course takes an integrated, in-depth view of foundational statistical concepts, modeling, and simulation techniques. Knowledge of typical system-level key performance parameters and their stochastic characterization is critical to the systems engineering process as the basis for decision-making from early system conceptualization through retirement. Relevant probability and statistics concepts are covered in context of SE decision points. Techniques in experimental design, data collection, analysis, and modeling of system metrics as a function of system use and environment are explored as they pertain to characterizing system, subsystem, and component performance. Finally, implementing models in analytic simulations to support requirements, design, upgrade, and replacement/retirement phases of the SE process provides the systems engineer with a solid foundation for making and justifying difficult decisions.
B889: systems_engineering | C889: EN.645.757 | D889: Foundations of Modeling and Simulation in Systems Engineering | E889: 3 | F889: Elective (Non-Core Engineering Discipline) | G889: Elective (Non-Core Engineering Discipline) | H889: Elective (Non-Core Engineering Discipline) | I889: Elective (Non-Core Engineering Discipline) | J889: Elective (Non-Core Engineering Discipline) | K889: Elective (Non-Core Engineering Discipline) | L889: Elective (Non-Core Engineering Discipline) | M889: Elective (Non-Core Engineering Discipline) | N889: Elective (Non-Core Engineering Discipline) | O889: Elective (Non-Core Engineering Discipline) | P889: Elective (Non-Core Engineering Discipline) | Q889: This course provides an introduction to the field of modeling and simulation (M&S) from the perspective of M&S as an essential tool for systems engineering. The course presents an overview of the M&S discipline, the model/simulation development process, the types of models and simulations used in the various phases of the systems engineering life cycle, and the verification, validation, and accreditation of models and simulation. The strengths and limitations of M&S are explored with respect to the application of M&S use in systems engineering. Examples are given for several types of systems, including both military and civilian systems. Statistical methods used in applying M&S in systems engineering are explained. The Arena process modeling tool is used for some examples, an individual assignment, and a team-based project. Upon completion of the course, the student will be able to explain when M&S will provide meaningful support to a technical program, select the appropriate modeling techniques for a given task, plan the development of a model/simulation and the modeling of its input data, and analyze the results of its execution to support decisions at key milestones of a system's life cycle.
B890: systems_engineering | C890: EN.645.758 | D890: Advanced Systems Modeling and Simulation | E890: 3 | F890: Elective (Non-Core Engineering Discipline) | G890: Elective (Non-Core Engineering Discipline) | H890: Elective (Non-Core Engineering Discipline) | I890: Elective (Non-Core Engineering Discipline) | J890: Elective (Non-Core Engineering Discipline) | K890: Elective (Non-Core Engineering Discipline) | L890: Elective (Non-Core Engineering Discipline) | M890: Elective (Non-Core Engineering Discipline) | N890: Elective (Non-Core Engineering Discipline) | O890: Elective (Non-Core Engineering Discipline) | P890: Elective (Non-Core Engineering Discipline) | Q890: This course provides in-depth exposure to the field of modeling and simulation (M&S) from the perspective of M&S as an essential tool for systems engineering. Advanced statistical methods are used to conduct requirements-driven simulation analysis and experimentation. The course provides treatment of advanced M&S topics, including methods for simulation interoperability and composability; modeling of the system environment, both natural and man-made; modeling of system costs; and the establishment of collaborative M&S environments. The course also explores continuous and real-time simulation. Students are exposed to the techniques used to form conceptual models of mechanical (both translational and rotational), electrical, fluid, thermal, biological, and hybrid systems. The conceptual models are transformed into mathematical models and implemented in a modern simulation package. State-of-the-art tools are explored, and each student is given the opportunity to conduct a simulation study of a complex system. Each student will present a case study and complete a project. Upon completion of the course, the student will be able to conduct or lead the development of the model of a complex physical system, model the input data, and analyze the results to support decisions at key milestones of a system's life cycle.
B891: systems_engineering | C891: EN.645.761 | D891: Systems Architecting | E891: 3 | F891: Elective (Non-Core Engineering Discipline) | G891: Elective (Non-Core Engineering Discipline) | H891: Elective (Non-Core Engineering Discipline) | I891: Elective (Non-Core Engineering Discipline) | J891: Elective (Non-Core Engineering Discipline) | K891: Elective (Non-Core Engineering Discipline) | L891: Elective (Non-Core Engineering Discipline) | M891: Elective (Non-Core Engineering Discipline) | N891: Elective (Non-Core Engineering Discipline) | O891: Elective (Non-Core Engineering Discipline) | P891: Elective (Non-Core Engineering Discipline) | Q891: This course provides a deep dive into the discipline of systems architecting by exploring systems engineering from the perspective of the systems architect. Students will learn how to define, analyze, and communicate architectures that address complex stakeholder needs, operational goals, and engineering constraints. Emphasis is placed on the development of architecture artifacts—including requirements, and functional, logical, physical, and interface models—as well as the application of a variety of architecture analysis tools and techniques. Students will gain the skills to not only construct architectures, but also to reason about them, manage their evolution, and ensure coherence across architecture views throughout the system development lifecycle.
B892: systems_engineering | C892: EN.645.764 | D892: Software Systems Engineering | E892: 3 | F892: Elective (Non-Core Engineering Discipline) | G892: Elective (Non-Core Engineering Discipline) | H892: Elective (Non-Core Engineering Discipline) | I892: Elective (Non-Core Engineering Discipline) | J892: Elective (Non-Core Engineering Discipline) | K892: Elective (Non-Core Engineering Discipline) | L892: Elective (Non-Core Engineering Discipline) | M892: Elective (Non-Core Engineering Discipline) | N892: Elective (Non-Core Engineering Discipline) | O892: Elective (Non-Core Engineering Discipline) | P892: Elective (Non-Core Engineering Discipline) | Q892: This course for systems engineers covers software engineering principles, artifacts, and approaches for the development of software systems. Topics include software engineering processes and metrics; real-time, distributed, configurable, and object-oriented software; alignment of software systems with overall system design; software-unique aspects of planning, requirements, architecture analysis, design, implementation, testing, and maintenance; understanding important software engineering constraints (performance, security, networking, etc.); and technology trends in software engineering today.
B893: systems_engineering | C893: EN.645.766 | D893: Systems Engineering Advanced Technology | E893: 3 | F893: Elective (Non-Core Engineering Discipline) | G893: Elective (Non-Core Engineering Discipline) | H893: Elective (Non-Core Engineering Discipline) | I893: Elective (Non-Core Engineering Discipline) | J893: Elective (Non-Core Engineering Discipline) | K893: Elective (Non-Core Engineering Discipline) | L893: Elective (Non-Core Engineering Discipline) | M893: Elective (Non-Core Engineering Discipline) | N893: Elective (Non-Core Engineering Discipline) | O893: Elective (Non-Core Engineering Discipline) | P893: Elective (Non-Core Engineering Discipline) | Q893: This course explores the frontier of advanced technology through the lens of systems engineering, equipping students to analyze, anticipate, and responsibly integrate emerging innovations across complex socio-technical ecosystems. Students will engage with over a dozen transformative technologies—including artificial intelligence, quantum computing, synthetic biology, advanced wireless networks, and space systems—while considering their systemic implications, ethical underpinnings, lifecycle integration, and historical evolution. Each technology is presented not as a standalone advancement but as an enabling component within interconnected systems that shape industries, societies, and the future of engineered environments.Grounded in systems approaches, the course emphasizes strategic foresight, ethical framing, and lifecycle adaptation. Students will assess not only the technical impacts of emerging technologies but also their broader ethical, social, and historical contexts. Through peer discussions, case studies, and cutting-edge journal reviews, learners will critically evaluate technology trajectories, identify stakeholder impacts, and examine cross-disciplinary challenges. Special attention is given to forecasting integration strategies that inform decision-making in real-world applications.The course's final project challenges students to develop a novel system concept that synthesizes two to five of the featured advanced technologies. This project integrates scenario development, stakeholder analysis, ethical reflection, and historical grounding. By the end of the course, students will have cultivated a forward-looking systems mindset, enhanced their ability to communicate complex technological impacts, and strengthened their capacity to lead responsibly in an era of rapid technological change.
B894: systems_engineering | C894: EN.645.767 | D894: System Conceptual Design | E894: 3 | F894: Elective (Non-Core Engineering Discipline) | G894: Elective (Non-Core Engineering Discipline) | H894: Elective (Non-Core Engineering Discipline) | I894: Elective (Non-Core Engineering Discipline) | J894: Elective (Non-Core Engineering Discipline) | K894: Elective (Non-Core Engineering Discipline) | L894: Elective (Non-Core Engineering Discipline) | M894: Elective (Non-Core Engineering Discipline) | N894: Elective (Non-Core Engineering Discipline) | O894: Elective (Non-Core Engineering Discipline) | P894: Elective (Non-Core Engineering Discipline) | Q894: This course addresses in detail the systems engineer’s responsibilities and activities during the conceptual phases of a system development program. Systems engineering tools commonly employed at this stage of a program are presented along with selected problems that illustrate both the applicability and limitations of commonly employed tools and procedures. The course steps through conceptual design beginning with analysis of needs and objectives and proceeding to the exploration of alternative concepts and the selection of a concept that best meets goals of performance, timeliness, and affordability. Topics include definition of operational scenarios, functional analysis, risk assessment, system tradeoffs, measures of effectiveness, and requirements formulation. Emphasis is on the application of these systems engineering techniques in a team environment to a class project. Students apply systems engineering methods learned from reading and lectures to the development of a realistic system in an ongoing project in a team format.
B895: systems_engineering | C895: EN.645.768 | D895: System Design & Integration | E895: 3 | F895: Elective (Non-Core Engineering Discipline) | G895: Elective (Non-Core Engineering Discipline) | H895: Elective (Non-Core Engineering Discipline) | I895: Elective (Non-Core Engineering Discipline) | J895: Elective (Non-Core Engineering Discipline) | K895: Elective (Non-Core Engineering Discipline) | L895: Elective (Non-Core Engineering Discipline) | M895: Elective (Non-Core Engineering Discipline) | N895: Elective (Non-Core Engineering Discipline) | O895: Elective (Non-Core Engineering Discipline) | P895: Elective (Non-Core Engineering Discipline) | Q895: This course addresses the systems engineering objectives, responsibilities, and activities during the demonstration and validation and the engineering and manufacturing development phases of a system development program. Systems engineering procedures and tools employed during these phases are identified and their use illustrated. Topics include the relationship between a system specification and the system design, systems engineering management plans, risk management, system development models, customer integration into the design process, and design disciplines and practices. The course uses a system problem scenario extensively to illustrate systems engineering principles and specific product design issues.
B896: systems_engineering | C896: EN.645.769 | D896: System Test & Evaluation | E896: 3 | F896: Elective (Non-Core Engineering Discipline) | G896: Elective (Non-Core Engineering Discipline) | H896: Elective (Non-Core Engineering Discipline) | I896: Elective (Non-Core Engineering Discipline) | J896: Elective (Non-Core Engineering Discipline) | K896: Elective (Non-Core Engineering Discipline) | L896: Elective (Non-Core Engineering Discipline) | M896: Elective (Non-Core Engineering Discipline) | N896: Elective (Non-Core Engineering Discipline) | O896: Elective (Non-Core Engineering Discipline) | P896: Elective (Non-Core Engineering Discipline) | Q896: This course focuses on the application of systems engineering principles to the test and evaluation of system elements and, ultimately, of the total system. Test requirements, selection of critical test parameters, analysis of test results, and determination of remedial action in the event of discrepancies are all systems engineering functions. Topics include validation and verification, similarities and differences in the nature of hardware and software testing, test tools and test procedures, testing during hardware-software integration, quality assurance test, environmental test, and operational test and evaluation. Student problems include scenario case studies using examples developed in the several previous courses.
... B935: Thesis | C935: EN.535.821 | D935: Master's Graduate Thesis | E935: 3 | F935: Thesis | G935: Thesis | H935: Thesis | I935: Thesis | J935: Thesis | K935: Thesis | L935: Thesis | M935: Thesis | N935: Thesis | O935: Thesis | P935: Thesis | Q935: Guidance and support for writing and completing the mechanical engineering master's thesis.

Sheet inf
A1: *** STEP 1: SELECT FROM LIST *** | B1: SP 20 | C1: YES
A2: Advanced Manufacturing | B2: SU 20 | C2: NO
A3: Aerospace Engineering - General | B3: FA 20
A4: Aerospace Engineering - Aerodynamics | B4: SP 21
A5: Aerospace Engineering - Dynamics and Control | B5: SU 21
A6: Aerospace Engineering - Structures and Materials | B6: FA 21
A7: Aerospace Engineering - Vehicle Design | B7: SP 22
A8: Biomechanical Engineering | B8: SU 22
A9: Fluid and Thermal Mechanics | B9: FA 22
A10: Hypersonic Technologies | B10: SP 23
A11: Ocean Engineering | B11: SU 23
A12: Robotics, Dynamics, and Controls | B12: FA 23
A13: Mechanics of Materials and Structures | B13: SP 24
B14: SU 24
B15: FA 24
B16: SP 25
B17: SU 25
B18: FA 25
B19: SP 26
B20: SU 26
B21: FA 26
B22: SP 27
B23: SU 27
B24: FA 27
B25: SP 28
... B93: FA 50

Sheet hp1
A1: *** STEP 02: SELECT GROUP 1 *** | B1: {=_xlfn._xlws.SORT(_xlfn.UNIQUE(_xlfn.VSTACK(_xlfn.ANCHORARRAY($A$2),$A$1)))} -> *** NA *** | C1: *** STEP 03: SELECT GROUP 1 *** | D1: {=_xlfn._xlws.SORT(_xlfn.UNIQUE(_xlfn.VSTACK(_xlfn.ANCHORARRAY($C$2),$C$1)))} -> *** NA *** | E1: *** STEP 04: SELECT GROUP 1 OR 2 *** | F1: {=_xlfn._xlws.SORT(_xlfn.UNIQUE(_xlfn.VSTACK(_xlfn.ANCHORARRAY($E$2),$E$1)))} -> *** NA *** | G1: *** STEP 05: SELECT GROUP 1 OR 2 *** | H1: {=_xlfn._xlws.SORT(_xlfn.UNIQUE(_xlfn.VSTACK($G$1,_xlfn.ANCHORARRAY($G$2))))} -> *** NA *** | I1: *** STEP 06: SELECT GROUP 1 OR 2 *** | J1: {=_xlfn._xlws.SORT(_xlfn.UNIQUE(_xlfn.VSTACK(_xlfn.ANCHORARRAY($I$2),$I$1)))} -> *** NA *** | K1: *** STEP 07: SELECT ELECTIVES *** | L1: {=_xlfn._xlws.SORT(_xlfn.UNIQUE(_xlfn.VSTACK(_xlfn.ANCHORARRAY($K$2),$K$1)))} -> *** STEP 07: SELECT ELECTIVES *** | M1: *** STEP 08: SELECT ELECTIVES *** | N1: {=_xlfn._xlws.SORT(_xlfn.UNIQUE(_xlfn.VSTACK(_xlfn.ANCHORARRAY($M$2),$M$1)))} -> *** STEP 08: SELECT ELECTIVES *** | O1: *** STEP 09: SELECT ELECTIVES *** | P1: {=_xlfn._xlws.SORT(_xlfn.UNIQUE(_xlfn.VSTACK(_xlfn.ANCHORARRAY($O$2),$O$1)))} -> *** STEP 09: SELECT ELECTIVES *** | Q1: *** STEP 10: SELECT ELECTIVES *** | R1: {=_xlfn._xlws.SORT(_xlfn.UNIQUE(_xlfn.VSTACK(_xlfn.ANCHORARRAY($Q$2),$Q$1)))} -> *** STEP 10: SELECT ELECTIVES ***
A2: {=_xlfn._xlws.SORT(_xlfn.LET( _xlpm.search_key, "*" & 'ME MS'!C10 & "*", _xlpm.target_col_index, _xlfn.XMATCH(_xlpm.search_key, cs!1:1, 2), _xlpm.target_col_data, _xlfn.CHOOSECOLS(cs!A:ZZ, _xlpm.target_col_index), _xlfn._xlws.FILTER(cs!C:C, (ISNUMBER(SEARCH("Group 1", _xlpm.target_col_data))), "*** NA ***") ))} -> *** NA *** | B2: *** STEP 02: SELECT GROUP 1 *** | C2: {=_xlfn._xlws.SORT(_xlfn.LET( _xlpm.search_key, "*" & 'ME MS'!C10 & "*", _xlpm.target_col_index, _xlfn.XMATCH(_xlpm.search_key, cs!1:1, 2), _xlpm.target_col_data, _xlfn.CHOOSECOLS(cs!A:ZZ, _xlpm.target_col_index), _xlfn._xlws.FILTER(cs!C:C, (ISNUMBER(SEARCH("Group 1", _xlpm.target_col_data))), "*** NA ***") ))} -> *** NA *** | D2: *** STEP 03: SELECT GROUP 1 *** | E2: {=_xlfn._xlws.SORT(_xlfn.LET( _xlpm.search_key, "*" & 'ME MS'!C10 & "*", _xlpm.target_col_index, _xlfn.XMATCH(_xlpm.search_key, cs!1:1, 2), _xlpm.target_col_data, _xlfn.CHOOSECOLS(cs!A:ZZ, _xlpm.target_col_index), _xlfn._xlws.FILTER(cs!C:C, ((ISNUMBER(SEARCH("Group 1", _xlpm.target_col_data))) + (ISNUMBER(SEARCH("Group 2", _xlpm.target_col_data)))), "*** NA ***") ))} -> *** NA *** | F2: *** STEP 04: SELECT GROUP 1 OR 2 *** | G2: {=_xlfn._xlws.SORT(_xlfn.LET( _xlpm.search_key, "*" & 'ME MS'!C10 & "*", _xlpm.target_col_index, _xlfn.XMATCH(_xlpm.search_key, cs!1:1, 2), _xlpm.target_col_data, _xlfn.CHOOSECOLS(cs!A:ZZ, _xlpm.target_col_index), _xlfn._xlws.FILTER(cs!C:C, ((ISNUMBER(SEARCH("Group 1", _xlpm.target_col_data))) + (ISNUMBER(SEARCH("Group 2", _xlpm.target_col_data)))), "*** NA ***") ))} -> *** NA *** | H2: *** STEP 05: SELECT GROUP 1 OR 2 *** | I2: {=_xlfn._xlws.SORT(_xlfn.LET( _xlpm.search_key, "*" & 'ME MS'!C10 & "*", _xlpm.target_col_index, _xlfn.XMATCH(_xlpm.search_key, cs!1:1, 2), _xlpm.target_col_data, _xlfn.CHOOSECOLS(cs!A:ZZ, _xlpm.target_col_index), _xlfn._xlws.FILTER(cs!C:C, ((ISNUMBER(SEARCH("Group 1", _xlpm.target_col_data))) + (ISNUMBER(SEARCH("Group 2", _xlpm.target_col_data)))), "*** NA ***") ))} -> *** NA *** | J2: *** STEP 06: SELECT GROUP 1 OR 2 *** | K2: {=_xlfn._xlws.SORT(_xlfn.LET( _xlpm.search_key, "*" & 'ME MS'!C10 & "*", _xlpm.target_col_index, _xlfn.XMATCH(_xlpm.search_key, cs!1:1, 2), _xlpm.target_col_data, _xlfn.CHOOSECOLS(cs!A:ZZ, _xlpm.target_col_index), _xlfn._xlws.FILTER(cs!C:C, ((ISNUMBER(SEARCH("Elective", _xlpm.target_col_data))) + (ISNUMBER(SEARCH("Group 1", _xlpm.target_col_data))) + (ISNUMBER(SEARCH("Group 2", _xlpm.target_col_data)))), "*** NA ***") ))} -> *** NA *** | L2: *** NA *** | M2: {=_xlfn._xlws.SORT(_xlfn.LET( _xlpm.search_key, "*" & 'ME MS'!C10 & "*", _xlpm.target_col_index, _xlfn.XMATCH(_xlpm.search_key, cs!1:1, 2), _xlpm.target_col_data, _xlfn.CHOOSECOLS(cs!A:ZZ, _xlpm.target_col_index), _xlfn._xlws.FILTER(cs!C:C, ((ISNUMBER(SEARCH("Elective", _xlpm.target_col_data))) + (ISNUMBER(SEARCH("Group 1", _xlpm.target_col_data))) + (ISNUMBER(SEARCH("Group 2", _xlpm.target_col_data)))), "*** NA ***") ))} -> *** NA *** | N2: *** NA *** | O2: {=_xlfn._xlws.SORT(_xlfn.LET( _xlpm.search_key, "*" & 'ME MS'!C10 & "*", _xlpm.target_col_index, _xlfn.XMATCH(_xlpm.search_key, cs!1:1, 2), _xlpm.target_col_data, _xlfn.CHOOSECOLS(cs!A:ZZ, _xlpm.target_col_index), _xlfn._xlws.FILTER(cs!C:C, ((ISNUMBER(SEARCH("Elective", _xlpm.target_col_data))) + (ISNUMBER(SEARCH("Group 1", _xlpm.target_col_data))) + (ISNUMBER(SEARCH("Group 2", _xlpm.target_col_data)))), "*** NA ***") ))} -> *** NA *** | P2: *** NA *** | Q2: {=_xlfn._xlws.SORT(_xlfn.LET( _xlpm.search_key, "*" & 'ME MS'!C10 & "*", _xlpm.target_col_index, _xlfn.XMATCH(_xlpm.search_key, cs!1:1, 2), _xlpm.target_col_data, _xlfn.CHOOSECOLS(cs!A:ZZ, _xlpm.target_col_index), _xlfn._xlws.FILTER(cs!C:C, ((ISNUMBER(SEARCH("Elective", _xlpm.target_col_data))) + (ISNUMBER(SEARCH("Group 1", _xlpm.target_col_data))) + (ISNUMBER(SEARCH("Group 2", _xlpm.target_col_data)))), "*** NA ***") ))} -> *** NA *** | R2: *** NA ***

Sheet ho2
A1: ='ME MS'!C10 -> *** STEP 1: SELECT FROM LIST ***
A2: ='ME MS'!B16 -> *** STEP 02: SELECT GROUP 1 *** | B2: EN.535.641
A3: ='ME MS'!B17 -> *** STEP 03: SELECT GROUP 1 ***
A4: ='ME MS'!B18 -> *** STEP 04: SELECT GROUP 1 OR 2 ***
A5: ='ME MS'!B19 -> *** STEP 05: SELECT GROUP 1 OR 2 ***
A6: ='ME MS'!B20 -> *** STEP 06: SELECT GROUP 1 OR 2 ***
A7: ='ME MS'!B22 -> *** STEP 07: SELECT ELECTIVES ***
A8: ='ME MS'!B23 -> *** STEP 08: SELECT ELECTIVES ***
A9: ='ME MS'!B24 -> *** STEP 09: SELECT ELECTIVES ***
A10: ='ME MS'!B25 -> *** STEP 10: SELECT ELECTIVES ***

Sheet cml
A1: EN.535.610 | B1: Computational Methods of Analysis
A2: EN.535.681 | B2: Design and Analysis of Experiments
A3: EN.535.742 | B3: Applied Machine Learning for Mechanical Engineers
A4: EN.535.743 | B4: Intermediate Applied Artificial Intelligence in Mechanical Engineering
A5: EN.535.766 | B5: Numerical Methods
